{
  "stats": {
    "suites": 1,
    "tests": 4,
    "passes": 4,
    "pending": 0,
    "failures": 0,
    "testsRegistered": 4,
    "passPercent": 100,
    "pendingPercent": 0,
    "other": 0,
    "hasOther": false,
    "skipped": 0,
    "hasSkipped": false,
    "start": "2023-06-08T18:53:18.798Z",
    "end": "2023-06-08T18:53:26.319Z",
    "duration": 7521
  },
  "results": [
    {
      "uuid": "252f5b6c-a7b2-4ac8-9625-352a594160b3",
      "title": "",
      "fullFile": "cypress/e2e/Signin&Signup.cy.js",
      "file": "cypress/e2e/Signin&Signup.cy.js",
      "beforeHooks": [],
      "afterHooks": [],
      "tests": [],
      "suites": [
        {
          "uuid": "a78b0186-d4cb-48da-86de-5babbf654a3d",
          "title": "Signin and Sinup flow tests",
          "fullFile": "",
          "file": "",
          "beforeHooks": [],
          "afterHooks": [],
          "tests": [
            {
              "title": "User registration",
              "fullTitle": "Signin and Sinup flow tests User registration",
              "timedOut": null,
              "duration": 2865,
              "state": "passed",
              "speed": "fast",
              "pass": true,
              "fail": false,
              "pending": false,
              "context": "[\n  \"screenshots/Signin&Signup.cy.js/Signin&Signup.cy.js/Signin and Sinup flow tests -- User registration (failed).png\",\n  \"videos/Signin&Signup.cy.js/Signin&Signup.cy.js.mp4\"\n]",
              "code": "const userName = _faker.faker.internet.userName();\ncy.contains(\"Sign up\").click();\ncy.get('[placeholder=\"Username\"]').type(userName);\ncy.checkA11y(null, null, null, true);\ncy.get('[placeholder=\"Email\"]').type(_faker.faker.internet.email());\ncy.get('[type=\"password\"]').type(\"teste123\");\ncy.contains(\"button\", \"Sign up\").click();\ncy.contains(\"Sign up\").should(\"not.exist\");\ncy.contains(userName).should(\"be.visible\");",
              "err": {},
              "uuid": "acea71ce-a46b-4d06-b20b-1e1d43434428",
              "parentUUID": "a78b0186-d4cb-48da-86de-5babbf654a3d",
              "isHook": false,
              "skipped": false
            },
            {
              "title": "Try to create a user with the same e-mail and username already registered",
              "fullTitle": "Signin and Sinup flow tests Try to create a user with the same e-mail and username already registered",
              "timedOut": null,
              "duration": 1491,
              "state": "passed",
              "speed": "fast",
              "pass": true,
              "fail": false,
              "pending": false,
              "context": "[\n  \"screenshots/Signin&Signup.cy.js/Signin&Signup.cy.js/Signin and Sinup flow tests -- Try to create a user with the same e-mail and username already registered (failed).png\",\n  \"videos/Signin&Signup.cy.js/Signin&Signup.cy.js.mp4\"\n]",
              "code": "cy.contains(\"Sign up\").click();\ncy.get('[placeholder=\"Username\"]').type(\"Caique Coelho\");\ncy.get('[placeholder=\"Email\"]').type(\"caiquedpfc@gmail.com\");\ncy.get('[type=\"password\"]').type(\"teste123\");\ncy.contains(\"button\", \"Sign up\").click();\ncy.contains(\"email has already been taken\").should(\"be.visible\");\ncy.contains(\"username has already been taken\").should(\"be.visible\");",
              "err": {},
              "uuid": "3bcccd35-727d-4d48-bbd0-9d725f8f5b9c",
              "parentUUID": "a78b0186-d4cb-48da-86de-5babbf654a3d",
              "isHook": false,
              "skipped": false
            },
            {
              "title": "User login",
              "fullTitle": "Signin and Sinup flow tests User login",
              "timedOut": null,
              "duration": 1806,
              "state": "passed",
              "speed": "fast",
              "pass": true,
              "fail": false,
              "pending": false,
              "context": "[\n  \"screenshots/Signin&Signup.cy.js/Signin&Signup.cy.js/Signin and Sinup flow tests -- User login (failed).png\",\n  \"videos/Signin&Signup.cy.js/Signin&Signup.cy.js.mp4\"\n]",
              "code": "cy.checkA11y(null, null, null, true);\ncy.contains(\"Sign in\").click();\ncy.get('[placeholder=\"Email\"]').type(\"caiquedpfc@gmail.com\"); // TODO Change to create custom command\ncy.get('[type=\"password\"]').type(\"test123\");\ncy.contains(\"button\", \"Sign in\").click();\ncy.contains(\"Sign up\").should(\"not.exist\");\ncy.contains(\"Caíque Coelho\").should(\"be.visible\");\ncy.checkA11y(null, null, null, true);",
              "err": {},
              "uuid": "443801ea-388f-4862-9c3a-2ff99a701828",
              "parentUUID": "a78b0186-d4cb-48da-86de-5babbf654a3d",
              "isHook": false,
              "skipped": false
            },
            {
              "title": "Try to log in with incorrect credentials",
              "fullTitle": "Signin and Sinup flow tests Try to log in with incorrect credentials",
              "timedOut": null,
              "duration": 1305,
              "state": "passed",
              "speed": "fast",
              "pass": true,
              "fail": false,
              "pending": false,
              "context": "[\n  \"screenshots/Signin&Signup.cy.js/Signin&Signup.cy.js/Signin and Sinup flow tests -- Try to log in with incorrect credentials (failed).png\",\n  \"videos/Signin&Signup.cy.js/Signin&Signup.cy.js.mp4\"\n]",
              "code": "cy.checkA11y(null, null, null, true);\ncy.contains(\"Sign in\").click();\ncy.get('[placeholder=\"Email\"]').type(\"caiquedpfc@gmail.com\"); // TODO Change to create custom command\ncy.get('[type=\"password\"]').type(\"test12\");\ncy.contains(\"button\", \"Sign in\").click();\ncy.contains(\"email or password is invalid\").should(\"be.visible\");",
              "err": {},
              "uuid": "0630aa1f-223f-478c-a0f3-1b51602ca6f6",
              "parentUUID": "a78b0186-d4cb-48da-86de-5babbf654a3d",
              "isHook": false,
              "skipped": false
            }
          ],
          "suites": [],
          "passes": [
            "acea71ce-a46b-4d06-b20b-1e1d43434428",
            "3bcccd35-727d-4d48-bbd0-9d725f8f5b9c",
            "443801ea-388f-4862-9c3a-2ff99a701828",
            "0630aa1f-223f-478c-a0f3-1b51602ca6f6"
          ],
          "failures": [],
          "pending": [],
          "skipped": [],
          "duration": 7467,
          "root": false,
          "rootEmpty": false,
          "_timeout": 2000
        }
      ],
      "passes": [],
      "failures": [],
      "pending": [],
      "skipped": [],
      "duration": 0,
      "root": true,
      "rootEmpty": true,
      "_timeout": 2000
    }
  ],
  "meta": {
    "mocha": {
      "version": "7.0.1"
    },
    "mochawesome": {
      "options": {
        "quiet": false,
        "reportFilename": "mochawesome",
        "saveHtml": false,
        "saveJson": true,
        "consoleReporter": "spec",
        "useInlineDiffs": false,
        "code": true
      },
      "version": "7.1.3"
    },
    "marge": {
      "options": {
        "id": "default",
        "overwrite": false,
        "html": false,
        "json": true,
        "reportDir": "cypress/reports/html/.jsons"
      },
      "version": "6.2.0"
    }
  }
}